memoy/single_port_ram.v
module single_port_ram (
    input  wire        clk,
    input  wire        we,   // write enable
    input  wire        cs,   // chip select
    input  wire [9:0]  addr, // endereco de 10-bit - RAM
    input  wire [7:0]  din,  // entrada de dados
    output      [7:0]  dout  // saida de dados
);

    reg [7:0] mem [0:1023];  // RAM de 1K x 8-bit
    reg [7:0] saida;

    assign dout = saida;

    always @(posedge clk) begin
        if (cs) begin
            if (we) begin
                mem[addr] <= din;
            end
            saida <= mem[addr];
        end
    end

endmodule

memoy/ram.v
module ram(
    input clk,
    input we,
    input [15:0] bits,
    input [7:0] din,
    output [7:0] dout1,
    output [7:0] dout2,
    output [7:0] dout3,
    output [7:0] dout4
);

    wire cs1, cs2, cs3, cs4;
    wire [9:0] addr;
    wire [5:0] seletor_mem;

    assign {seletor_mem, addr} = bits;

    assign cs1 = (seletor_mem == 6'h0) ? 1'b1 : 1'b0;
    assign cs2 = (seletor_mem == 6'h1) ? 1'b1 : 1'b0;
    assign cs3 = (seletor_mem == 6'h2) ? 1'b1 : 1'b0;
    assign cs4 = (seletor_mem == 6'h3) ? 1'b1 : 1'b0;
    
    single_port_ram ram1 (
        .clk(clk),
        .we(we),
        .cs(cs1),
        .addr(addr),
        .din(din),
        .dout(dout1)
    );

    single_port_ram ram2 (
        .clk(clk),
        .we(we),
        .cs(cs2),
        .addr(addr),
        .din(din),
        .dout(dout2)
    );


    single_port_ram ram3 (
        .clk(clk),
        .we(we),
        .cs(cs3),
        .addr(addr),
        .din(din),
        .dout(dout3)
    );

    single_port_ram ram4 (
        .clk(clk),
        .we(we),
        .cs(cs4),
        .addr(addr),
        .din(din),
        .dout(dout4)
    );

endmodule

memoy/testbench.v
module testbench;

    reg clk, we;
    reg [15:0] bits;
    reg [7:0] din;
    wire [7:0] dout1, dout2, dout3, dout4;

    ram RAM(
        .clk(clk),
        .we(we),
        .bits(bits),
        .din(din),
        .dout1(dout1),
        .dout2(dout2),
        .dout3(dout3),
        .dout4(dout4)
    );

    initial clk = 1'b0;

    always #5 clk = ~clk;

    initial begin
        $dumpfile("teste.vcd");
        $dumpvars(0,testbench);
        $monitor("we = %b  | bits = %b | din = %b | dout1 = %b | dout2 = %b | dout3 = %b | dout4 = %b", we, bits, din, dout1, dout2, dout3, dout4);

        we = 1'b0;
        
        #10 we = 1'b1; 
        bits = 16'b000000_0000000000;
        din = 8'h01;
        
        #10   we = 1'b0;

        #10 we = 1'b1; 
        bits = 16'b000001_0001000000;
        din = 8'h02;

        #10   we = 1'b0;

        #10 we = 1'b1; 
        bits = 16'b000010_0000100000;
        din = 8'h04;

        #10   we = 1'b0;

        #10 we = 1'b1; 
        bits = 16'b000011_1000000001;
        din = 8'h08;

        #10   we = 1'b0;

        //Não escreve nas memórias
        #10 we = 1'b1; 
        bits = 16'b010000_1111111111;
        din = 8'h0f;

        #10   we = 1'b0;

        //Não escreve nas memórias
        #10 we = 1'b1; 
        bits = 16'b111000_1111111111;
        din = 8'h0f;


        #100   we = 1'b0;

        #100 $finish();

    end

endmodule

memoy/teste.vcd
$date
	Tue May 19 15:06:17 2026
$end
$version
	Icarus Verilog
$end
$timescale
	1s
$end
$scope module testbench $end
$var wire 8 ! dout4 [7:0] $end
$var wire 8 " dout3 [7:0] $end
$var wire 8 # dout2 [7:0] $end
$var wire 8 $ dout1 [7:0] $end
$var reg 16 % bits [15:0] $end
$var reg 1 & clk $end
$var reg 8 ' din [7:0] $end
$var reg 1 ( we $end
$scope module RAM $end
$var wire 16 ) bits [15:0] $end
$var wire 1 & clk $end
$var wire 8 * din [7:0] $end
$var wire 1 ( we $end
$var wire 6 + seletor_mem [5:0] $end
$var wire 8 , dout4 [7:0] $end
$var wire 8 - dout3 [7:0] $end
$var wire 8 . dout2 [7:0] $end
$var wire 8 / dout1 [7:0] $end
$var wire 1 0 cs4 $end
$var wire 1 1 cs3 $end
$var wire 1 2 cs2 $end
$var wire 1 3 cs1 $end
$var wire 10 4 addr [9:0] $end
$scope module ram1 $end
$var wire 10 5 addr [9:0] $end
$var wire 1 & clk $end
$var wire 1 3 cs $end
$var wire 8 6 din [7:0] $end
$var wire 8 7 dout [7:0] $end
$var wire 1 ( we $end
$var reg 8 8 saida [7:0] $end
$upscope $end
$scope module ram2 $end
$var wire 10 9 addr [9:0] $end
$var wire 1 & clk $end
$var wire 1 2 cs $end
$var wire 8 : din [7:0] $end
$var wire 8 ; dout [7:0] $end
$var wire 1 ( we $end
$var reg 8 < saida [7:0] $end
$upscope $end
$scope module ram3 $end
$var wire 10 = addr [9:0] $end
$var wire 1 & clk $end
$var wire 1 1 cs $end
$var wire 8 > din [7:0] $end
$var wire 8 ? dout [7:0] $end
$var wire 1 ( we $end
$var reg 8 @ saida [7:0] $end
$upscope $end
$scope module ram4 $end
$var wire 10 A addr [9:0] $end
$var wire 1 & clk $end
$var wire 1 0 cs $end
$var wire 8 B din [7:0] $end
$var wire 8 C dout [7:0] $end
$var wire 1 ( we $end
$var reg 8 D saida [7:0] $end
$upscope $end
$upscope $end
$upscope $end
$enddefinitions $end
$comment Show the parameter values. $end
$dumpall
$end
#0
$dumpvars
bx D
bx C
bx B
bx A
bx @
bx ?
bx >
bx =
bx <
bx ;
bx :
bx 9
bx 8
bx 7
bx 6
bx 5
bx 4
x3
x2
x1
x0
bx /
bx .
bx -
bx ,
bx +
bx *
bx )
0(
bx '
0&
bx %
bx $
bx #
bx "
bx !
$end
#5
1&
#10
13
02
01
00
b0 +
b0 4
b0 5
b0 9
b0 =
b0 A
0&
b1 '
b1 *
b1 6
b1 :
b1 >
b1 B
b0 %
b0 )
1(
#15
1&
#20
0&
0(
#25
b1 $
b1 /
b1 7
b1 8
1&
#30
03
12
b1 +
b1000000 4
b1000000 5
b1000000 9
b1000000 =
b1000000 A
0&
b10 '
b10 *
b10 6
b10 :
b10 >
b10 B
b10001000000 %
b10001000000 )
1(
#35
1&
#40
0&
0(
#45
b10 #
b10 .
b10 ;
b10 <
1&
#50
02
11
b10 +
b100000 4
b100000 5
b100000 9
b100000 =
b100000 A
0&
b100 '
b100 *
b100 6
b100 :
b100 >
b100 B
b100000100000 %
b100000100000 )
1(
#55
1&
#60
0&
0(
#65
b100 "
b100 -
b100 ?
b100 @
1&
#70
01
10
b11 +
b1000000001 4
b1000000001 5
b1000000001 9
b1000000001 =
b1000000001 A
0&
b1000 '
b1000 *
b1000 6
b1000 :
b1000 >
b1000 B
b111000000001 %
b111000000001 )
1(
#75
1&
#80
0&
0(
#85
b1000 !
b1000 ,
b1000 C
b1000 D
1&
#90
00
b10000 +
b1111111111 4
b1111111111 5
b1111111111 9
b1111111111 =
b1111111111 A
0&
b1111 '
b1111 *
b1111 6
b1111 :
b1111 >
b1111 B
b100001111111111 %
b100001111111111 )
1(
#95
1&
#100
0&
0(
#105
1&
#110
b111000 +
0&
b1110001111111111 %
b1110001111111111 )
1(
#115
1&
#120
0&
#125
1&
#130
0&
#135
1&
#140
0&
#145
1&
#150
0&
#155
1&
#160
0&
#165
1&
#170
0&
#175
1&
#180
0&
#185
1&
#190
0&
#195
1&
#200
0&
#205
1&
#210
0&
0(
