Arithmetic Circuits/half_adder/half_adder.v
module half_adder(
    input a,
    input b,
    output sum,
    output cout
);

    assign sum = a ^ b; //a xor b
    assign cout = a & b; // a and b    



endmodule

Arithmetic Circuits/full_adder/full_adder.v
module full_adder(
    input a,
    input b,
    input cin,
    output sum,
    output cout
);
    wire cout1, cout2, sum0;

    


    half_adder ad1(
        .a(a),
        .b(b),
        .sum(sum0),
        .cout(cout1)
    );

    half_adder ad2(
        .a(sum0),
        .b(cin),
        .sum(sum),
        .cout(cout2)
    );

    assign cout = cout1 | cout2;

endmodule

Arithmetic Circuits/full_adder/testbench.v
module testbench;

    reg a, b, cin;
    wire sum, cout;


    full_adder ad(
        .a(a),
        .b(b),
        .cin(cin),
        .sum(sum),
        .cout(cout)
    );


    task expect;
        input valor_esperado;
        
        if(valor_esperado !== sum)begin 
            $display("Teste falhou!!!");
            $display("a = %b | b = %b | cin = %b | sum = %b | cout = %b ", a, b, cin, sum, cout);
            $display("Valor esperado para sum = %b", valor_esperado);
        end
        else begin
            $display("a = %b | b = %b | cin = %b | sum = %b | cout = %b ", a, b, cin, sum, cout);
        end
    endtask



    initial begin
        $dumpfile("teste.vcd");
        $dumpvars(0,testbench);
        
           cin = 1'b0; a = 1'b0; b=1'b0; #3 expect(1'b0);
        #2 cin = 1'b0; a = 1'b0; b=1'b1; #3 expect(1'b1); 
        #2 cin = 1'b0; a = 1'b1; b=1'b0; #3 expect(1'b1);
        #2 cin = 1'b0; a = 1'b1; b=1'b1; #3 expect(1'b0);
        #2 cin = 1'b1; a = 1'b0; b=1'b0; #3 expect(1'b1);
        #2 cin = 1'b1; a = 1'b0; b=1'b1; #3 expect(1'b0);
        #2 cin = 1'b1; a = 1'b1; b=1'b0; #3 expect(1'b0);
        #2 cin = 1'b1; a = 1'b1; b=1'b1; #3 expect(1'b1);

    end


endmodule

Arithmetic Circuits/full_adder/teste.vcd
$date
	Sun Apr  5 12:27:13 2026
$end
$version
	Icarus Verilog
$end
$timescale
	1s
$end
$scope module testbench $end
$var wire 1 ! sum $end
$var wire 1 " cout $end
$var reg 1 # a $end
$var reg 1 $ b $end
$var reg 1 % cin $end
$scope module ad $end
$var wire 1 # a $end
$var wire 1 $ b $end
$var wire 1 % cin $end
$var wire 1 " cout $end
$var wire 1 & sum0 $end
$var wire 1 ! sum $end
$var wire 1 ' cout2 $end
$var wire 1 ( cout1 $end
$scope module ad1 $end
$var wire 1 # a $end
$var wire 1 $ b $end
$var wire 1 ( cout $end
$var wire 1 & sum $end
$upscope $end
$scope module ad2 $end
$var wire 1 & a $end
$var wire 1 % b $end
$var wire 1 ' cout $end
$var wire 1 ! sum $end
$upscope $end
$upscope $end
$scope task expect $end
$var reg 1 ) valor_esperado $end
$upscope $end
$upscope $end
$enddefinitions $end
$comment Show the parameter values. $end
$dumpall
$end
#0
$dumpvars
x)
0(
0'
0&
0%
0$
0#
0"
0!
$end
#3
0)
#5
1!
1&
1$
#8
1)
#10
0$
1#
#15
0!
1"
0&
1(
1$
#18
0)
#20
0"
0(
1!
0$
0#
1%
#23
1)
#25
1"
0!
1'
1&
1$
#28
0)
#30
0$
1#
#35
1!
0'
0&
1(
1$
#38
1)
