Arithmetic Circuits/half_adder/half_adder.v
module half_adder(
    input a,
    input b,
    output sum,
    output cout
);

    assign sum = a ^ b; //a xor b
    assign cout = a & b; // a and b    



endmodule

Arithmetic Circuits/half_adder/testbench.v
module testbench;


    reg a, b;
    wire sum, cout;


    half_adder adder(
        .a(a),
        .b(b),
        .sum(sum),
        .cout(cout)
    );


    task expect;
        input experado_out;
        if(sum !== experado_out)begin
            $display("Teste falho!!!!!!!");
            $display("a = %b | b = %b | sum  %b | cout = %b", a, b, sum, cout);
            $display("Valor de esperado = %b", experado_out);
            $finish;
        end
        else begin
            $display("a = %b | b = %b | sum  %b | cout = %b", a, b, sum, cout);
        end

    endtask

    initial begin
       $dumpfile("teste.vcd");
       $dumpvars(0,testbench);
       
       #1;

       #2 a=1'b0; b=1'b0; #1 expect(1'b0);
       #2 a=1'b0; b=1'b1; #1 expect(1'b1);
       #2 a=1'b1; b=1'b0; #1 expect(1'b1);
       #2 a=1'b1; b=1'b1; #1 expect(1'b0);



    end 



endmodule

Arithmetic Circuits/half_adder/teste.vcd
$date
	Sat Apr  4 19:51:05 2026
$end
$version
	Icarus Verilog
$end
$timescale
	1s
$end
$scope module testbench $end
$var wire 1 ! sum $end
$var wire 1 " cout $end
$var reg 1 # a $end
$var reg 1 $ b $end
$scope module adder $end
$var wire 1 # a $end
$var wire 1 $ b $end
$var wire 1 " cout $end
$var wire 1 ! sum $end
$upscope $end
$scope task expect $end
$var reg 1 % experado_out $end
$upscope $end
$upscope $end
$enddefinitions $end
$comment Show the parameter values. $end
$dumpall
$end
#0
$dumpvars
x%
x$
x#
x"
x!
$end
#3
0!
0"
0$
0#
#4
0%
#6
1!
1$
#7
1%
#9
0$
1#
#12
0!
1"
1$
#13
0%
